audioblock/__init__.py
audioblock/admin.py
audioblock/models.py
audioblock/urls.py
audioblock/views.py
audioblock/management/__init__.py
audioblock/management/commands/__init__.py
audioblock/migrations/0001_initial.py
audioblock/migrations/__init__.py
audioblock/templates/audioblock/audioblock.html
audioblock/templates/audioblock/audioblock_css.html
audioblock/templates/audioblock/audioblock_js.html
django_audioblock-1.1.0.dist-info/DESCRIPTION.rst
django_audioblock-1.1.0.dist-info/METADATA
django_audioblock-1.1.0.dist-info/RECORD
django_audioblock-1.1.0.dist-info/WHEEL
django_audioblock-1.1.0.dist-info/metadata.json
django_audioblock-1.1.0.dist-info/top_level.txt
