Metadata-Version: 2.0
Name: django-audioblock
Version: 1.1.0
Summary: Audio PageBlock
Home-page: https://github.com/ccnmtl/django-audioblock
Author: Anders Pearson
Author-email: anders@columbia.edu
License: BSD
Platform: any
Requires-Dist: django-pagetree (>=1.1.2)
